{
  "721": {
    "6be221e45858b912b1efb4d79d6c239f24239ef73e99945e6cc33ada": {
      "thebigsundae34": {
        "name": "thebigsundae34",
        "image": "ipfs://QmYNDvYjPB4paDP4zmG2Krr8uYNb6wcc9CcU9Lf8WxujMd",
        "mediaType": "image/png",
        "description": "34",
        "files": [
          {
            "name": "34",
            "mediaType": "image/png",
            "src": "ipfs://QmYNDvYjPB4paDP4zmG2Krr8uYNb6wcc9CcU9Lf8WxujMd"
          }
        ],
        "sundae": "sunville",
  "background": "34",
  "sexuality": "male",
  "flavor": "pistachio"
      }
    },
    "version": "1.0"
  }
}
